xontrib/spec_mod/__init__.py
xontrib/spec_mod/to_dict.py
xontrib_spec_mod-0.0.5.dist-info/LICENSE
xontrib_spec_mod-0.0.5.dist-info/METADATA
xontrib_spec_mod-0.0.5.dist-info/WHEEL
xontrib_spec_mod-0.0.5.dist-info/top_level.txt
xontrib_spec_mod-0.0.5.dist-info/RECORD
