Metadata-Version: 2.1
Name: xontrib-spec-mod
Version: 0.0.5
Summary: Library of xonsh subprocess specification modifiers.
Author-email: anki-code <a@a.a>
License: MIT License
Project-URL: Homepage, https://github.com/anki-code/xontrib-spec-mod
Project-URL: Documentation, https://github.com/anki-code/xontrib-spec-mod/blob/master/README.md
Project-URL: Code, https://github.com/anki-code/xontrib-spec-mod
Project-URL: Issue tracker, https://github.com/anki-code/xontrib-spec-mod/issues
Platform: any
Classifier: Programming Language :: Python :: 3
Classifier: License :: OSI Approved :: MIT License
Classifier: Operating System :: OS Independent
Classifier: Topic :: System :: Shells
Classifier: Topic :: System :: System Shells
Classifier: Topic :: Terminals
Requires-Python: >=3.8
License-File: LICENSE
Requires-Dist: xonsh >=0.17.0
Provides-Extra: dev
Requires-Dist: pytest >=7.0 ; extra == 'dev'
Provides-Extra: dict
Requires-Dist: demjson3 ; extra == 'dict'
Provides-Extra: yaml
Requires-Dist: pyyaml ; extra == 'yaml'
